Metadata-Version: 2.1
Name: hashtools
Version: 0.3.0
Summary: Hash tools collection, like md5, sha1, sha256 and many other hash tools.
Home-page: https://github.com/zencore-cn/zencore-issues
Author: zencore
Author-email: dobetter@zencore.cn
License: MIT
Keywords: hashtools
Platform: UNKNOWN
Classifier: Development Status :: 5 - Production/Stable
Classifier: Intended Audience :: Developers
Classifier: Topic :: Software Development :: Libraries :: Python Modules
Classifier: License :: OSI Approved :: MIT License
Classifier: Programming Language :: Python :: 3
Classifier: Programming Language :: Python :: 3 :: Only
